<!-- - - - - - - - - - - -
#########################
##### H7SB Backpacks ####
### 7 Days to Die Mod ###
#########################
####### Eihwaz © ########
##### NO REUPLAOD! ######
#### CC BY-NC-ND-SA #####
#########################
- - - - - - - - - - - -->
<eihwaz.de>
<append xpath="/items/item[@name='h7sb_smallBackpack']"><property name="UnlockedBy" value="perkLightArmor"/></append>
<append xpath="/items/item[@name='h7sb_blueBackpack']"><property name="UnlockedBy" value="perkLightArmor"/></append>
<append xpath="/items/item[@name='h7sb_orangeBackpack']"><property name="UnlockedBy" value="perkLightArmor"/></append>
<append xpath="/items/item[@name='h7sb_largeBackpack']"><property name="UnlockedBy" value="perkLightArmor,perkNeedleAndThreadPockets"/></append>
</eihwaz.de>